<PIPELINE>
	<MODULE seq="001" name="FILE PROCESSING">
		<FUNCTION name="LOAD FILE">
			<REGEXP>tape.jpeg</REGEXP>
			<OUTPUT>IMAGE12</OUTPUT>
		</FUNCTION>
	</MODULE>
	<MODULE seq="002" name="FILE PROCESSING">
		<FUNCTION name="NORMALIZE">
			<INPUT>IMAGE12</INPUT>
			<OUTPUT>IMAGE1</OUTPUT>
			<ASHOW>TRUE</ASHOW>
			<WINDOWSNAME>NULL</WINDOWSNAME>
			<!-- MAXMIN or LOG-->
			<MAXINT>1</MAXINT>
			<MININT>0</MININT>
			<TYPE>LOG</TYPE>
		</FUNCTION>
	</MODULE>
	<MODULE seq="002" name="IMAGE PROCESSING">
		<FUNCTION name="THRESHOLD">
			<INPUT>IMAGE1</INPUT>
			<THRESHOLD>0.7</THRESHOLD>
			<THRESHOLD_TYPE>THRESH_BINARY_INV</THRESHOLD_TYPE>
			<MAX_THRESHOLD>1</MAX_THRESHOLD>
			<ASHOW>TRUE</ASHOW>
			<WINDOWSNAME>THRESHOLD</WINDOWSNAME>
			<OUTPUT>IMAGE2</OUTPUT>
		</FUNCTION>
	</MODULE>
	<MODULE seq="003" name="IMAGE PROCESSING">
		<FUNCTION name="MAKE BRUSH">
			<ASHOW>FALSE</ASHOW>
			<WINDOWSNAME>MY BRUSH</WINDOWSNAME>
			<BRUSH_SIZE_X>3</BRUSH_SIZE_X>
			<BRUSH_SIZE_Y>3</BRUSH_SIZE_Y>
			<BRUSH_TYPE>GAUSSIAN_SHAPE</BRUSH_TYPE>
			<SIGMA>5</SIGMA>
			<OUTPUT>BRUSH NUMBER 1</OUTPUT>
		</FUNCTION>
	</MODULE>
	<MODULE seq="004" name="IMAGE PROCESSING">
		<FUNCTION name="MORPHOLOGICAL OPERATION">
			<ASHOW>TRUE</ASHOW>
			<WINDOWSNAME>OPENING</WINDOWSNAME>
			<OPERATION>OPENING</OPERATION>
			<ITERATIONS>1</ITERATIONS>
			<INPUT>IMAGE2</INPUT>
			<BRUSH>BRUSH NUMBER 1</BRUSH>
			<OUTPUT>IMAGE3</OUTPUT>
		</FUNCTION>
	</MODULE>
	<MODULE seq="005" name="IMAGE PROCESSING">
		<FUNCTION name="FIND CONTOURS">
			<ASHOW>TRUE</ASHOW>
			<WINDOWSNAME>CONTOURS</WINDOWSNAME>
			<COLOUR>RED</COLOUR>
			<THICKNESS>2</THICKNESS>
			<RETRIEVAL_MODE>CONNECTED COMPONENTS</RETRIEVAL_MODE>
			<APPROXIMATION>NONE</APPROXIMATION>
			<INPUT>IMAGE3</INPUT>
			<OUTPUT>OBJECTS_IM</OUTPUT>
			<SAVE_OBJECTS>OBJECTS</SAVE_OBJECTS>
		</FUNCTION>
	</MODULE>
	<MODULE seq="006" name="IMAGE PROCESSING">
		<FUNCTION name="FLOODFILL">
		<ASHOW>TRUE</ASHOW>
			<WINDOWSNAME>Filling coordinates</WINDOWSNAME>
			<!-- DEFAULT_COLOR_SEED, RGB(0,0,0), #FFFFFF, RED, GREEN... OR RANDOM -->
			<COLOUR>RANDOM</COLOUR>
			<SEEDS>OBJECTS</SEEDS>
			<LOW_DIFF>0</LOW_DIFF>
			<UP_DIFF>0</UP_DIFF>
			<INPUT>IMAGE3</INPUT>
			<OUTPUT>IMAGE6</OUTPUT>
		</FUNCTION>
	</MODULE>
</PIPELINE>
